{
  "url": "http://localhost:3001/",
  "violations": [
    {
      "id": "color-contrast",
      "impact": "serious",
      "tags": [
        "cat.color",
        "wcag2aa",
        "wcag143",
        "TTv5",
        "TT13.c",
        "EN-301-549",
        "EN-9.1.4.3",
        "ACT",
        "RGAAv4",
        "RGAA-3.2.1"
      ],
      "description": "Ensure the contrast between foreground and background colors meets WCAG 2 AA minimum contrast ratio thresholds",
      "help": "Elements must meet minimum color contrast ratio thresholds",
      "helpUrl": "https://dequeuniversity.com/rules/axe/4.11/color-contrast?application=axeAPI",
      "nodes": [
        {
          "any": [
            {
              "id": "color-contrast",
              "data": {
                "fgColor": "#00a63e",
                "bgColor": "#ffffff",
                "contrastRatio": 3.24,
                "fontSize": "9.0pt (12px)",
                "fontWeight": "normal",
                "messageKey": null,
                "expectedContrastRatio": "4.5:1"
              },
              "relatedNodes": [
                {
                  "html": "<div data-slot=\"card\" class=\"bg-card text-card-foreground flex flex-col gap-6 rounded-xl border py-6 shadow-sm\">",
                  "target": [
                    ".lg\\:grid-cols-4 > .bg-card.text-card-foreground.gap-6:nth-child(1)"
                  ]
                }
              ],
              "impact": "serious",
              "message": "Element has insufficient color contrast of 3.24 (foreground color: #00a63e, background color: #ffffff, font size: 9.0pt (12px), font weight: normal). Expected contrast ratio of 4.5:1"
            }
          ],
          "all": [],
          "none": [],
          "impact": "serious",
          "html": "<p class=\"text-xs text-green-600 mt-1\">+12.5%<!-- --> from last month</p>",
          "target": [
            ".bg-card.text-card-foreground.gap-6:nth-child(1) > .px-6[data-slot=\"card-content\"] > .text-green-600.mt-1"
          ],
          "failureSummary": "Fix any of the following:\n  Element has insufficient color contrast of 3.24 (foreground color: #00a63e, background color: #ffffff, font size: 9.0pt (12px), font weight: normal). Expected contrast ratio of 4.5:1"
        },
        {
          "any": [
            {
              "id": "color-contrast",
              "data": {
                "fgColor": "#00a63e",
                "bgColor": "#ffffff",
                "contrastRatio": 3.24,
                "fontSize": "9.0pt (12px)",
                "fontWeight": "normal",
                "messageKey": null,
                "expectedContrastRatio": "4.5:1"
              },
              "relatedNodes": [
                {
                  "html": "<div data-slot=\"card\" class=\"bg-card text-card-foreground flex flex-col gap-6 rounded-xl border py-6 shadow-sm\">",
                  "target": [
                    ".lg\\:grid-cols-4 > .bg-card.text-card-foreground.gap-6:nth-child(2)"
                  ]
                }
              ],
              "impact": "serious",
              "message": "Element has insufficient color contrast of 3.24 (foreground color: #00a63e, background color: #ffffff, font size: 9.0pt (12px), font weight: normal). Expected contrast ratio of 4.5:1"
            }
          ],
          "all": [],
          "none": [],
          "impact": "serious",
          "html": "<p class=\"text-xs text-green-600 mt-1\">+5.2%<!-- --> from last month</p>",
          "target": [
            ".bg-card.text-card-foreground.gap-6:nth-child(2) > .px-6[data-slot=\"card-content\"] > .text-green-600.mt-1"
          ],
          "failureSummary": "Fix any of the following:\n  Element has insufficient color contrast of 3.24 (foreground color: #00a63e, background color: #ffffff, font size: 9.0pt (12px), font weight: normal). Expected contrast ratio of 4.5:1"
        },
        {
          "any": [
            {
              "id": "color-contrast",
              "data": {
                "fgColor": "#00a63e",
                "bgColor": "#ffffff",
                "contrastRatio": 3.24,
                "fontSize": "9.0pt (12px)",
                "fontWeight": "normal",
                "messageKey": null,
                "expectedContrastRatio": "4.5:1"
              },
              "relatedNodes": [
                {
                  "html": "<div data-slot=\"card\" class=\"bg-card text-card-foreground flex flex-col gap-6 rounded-xl border py-6 shadow-sm\">",
                  "target": [
                    ".bg-card.text-card-foreground.gap-6:nth-child(3)"
                  ]
                }
              ],
              "impact": "serious",
              "message": "Element has insufficient color contrast of 3.24 (foreground color: #00a63e, background color: #ffffff, font size: 9.0pt (12px), font weight: normal). Expected contrast ratio of 4.5:1"
            }
          ],
          "all": [],
          "none": [],
          "impact": "serious",
          "html": "<p class=\"text-xs text-green-600 mt-1\">+18.3%<!-- --> from last month</p>",
          "target": [
            ".bg-card.text-card-foreground.gap-6:nth-child(3) > .px-6[data-slot=\"card-content\"] > .text-green-600.mt-1"
          ],
          "failureSummary": "Fix any of the following:\n  Element has insufficient color contrast of 3.24 (foreground color: #00a63e, background color: #ffffff, font size: 9.0pt (12px), font weight: normal). Expected contrast ratio of 4.5:1"
        },
        {
          "any": [
            {
              "id": "color-contrast",
              "data": {
                "fgColor": "#00a63e",
                "bgColor": "#ffffff",
                "contrastRatio": 3.24,
                "fontSize": "9.0pt (12px)",
                "fontWeight": "normal",
                "messageKey": null,
                "expectedContrastRatio": "4.5:1"
              },
              "relatedNodes": [
                {
                  "html": "<div data-slot=\"card\" class=\"bg-card text-card-foreground flex flex-col gap-6 rounded-xl border py-6 shadow-sm\">",
                  "target": [
                    ".bg-card.text-card-foreground.gap-6:nth-child(4)"
                  ]
                }
              ],
              "impact": "serious",
              "message": "Element has insufficient color contrast of 3.24 (foreground color: #00a63e, background color: #ffffff, font size: 9.0pt (12px), font weight: normal). Expected contrast ratio of 4.5:1"
            }
          ],
          "all": [],
          "none": [],
          "impact": "serious",
          "html": "<p class=\"text-xs text-green-600 mt-1\">+3.1%<!-- --> from last month</p>",
          "target": [
            ".bg-card.text-card-foreground.gap-6:nth-child(4) > .px-6[data-slot=\"card-content\"] > .text-green-600.mt-1"
          ],
          "failureSummary": "Fix any of the following:\n  Element has insufficient color contrast of 3.24 (foreground color: #00a63e, background color: #ffffff, font size: 9.0pt (12px), font weight: normal). Expected contrast ratio of 4.5:1"
        }
      ]
    },
    {
      "id": "landmark-main-is-top-level",
      "impact": "moderate",
      "tags": [
        "cat.semantics",
        "best-practice"
      ],
      "description": "Ensure the main landmark is at top level",
      "help": "Main landmark should not be contained in another landmark",
      "helpUrl": "https://dequeuniversity.com/rules/axe/4.11/landmark-main-is-top-level?application=axeAPI",
      "nodes": [
        {
          "any": [
            {
              "id": "landmark-is-top-level",
              "data": {
                "role": "main"
              },
              "relatedNodes": [],
              "impact": "moderate",
              "message": "The main landmark is contained in another landmark."
            }
          ],
          "all": [],
          "none": [],
          "impact": "moderate",
          "html": "<main class=\"flex-1 overflow-y-auto p-6\">",
          "target": [
            "main > .bg-gray-50.h-screen.flex > main"
          ],
          "failureSummary": "Fix any of the following:\n  The main landmark is contained in another landmark."
        }
      ]
    },
    {
      "id": "landmark-no-duplicate-main",
      "impact": "moderate",
      "tags": [
        "cat.semantics",
        "best-practice"
      ],
      "description": "Ensure the document has at most one main landmark",
      "help": "Document should not have more than one main landmark",
      "helpUrl": "https://dequeuniversity.com/rules/axe/4.11/landmark-no-duplicate-main?application=axeAPI",
      "nodes": [
        {
          "any": [
            {
              "id": "page-no-duplicate-main",
              "data": null,
              "relatedNodes": [
                {
                  "html": "<main class=\"flex-1 overflow-y-auto p-6\">",
                  "target": [
                    "main > .bg-gray-50.h-screen.flex > main"
                  ]
                }
              ],
              "impact": "moderate",
              "message": "Document has more than one main landmark"
            }
          ],
          "all": [],
          "none": [],
          "impact": "moderate",
          "html": "<main class=\"flex-1 overflow-y-auto p-6\">",
          "target": [
            "body > .bg-gray-50.h-screen.flex > main"
          ],
          "failureSummary": "Fix any of the following:\n  Document has more than one main landmark"
        }
      ]
    },
    {
      "id": "landmark-unique",
      "impact": "moderate",
      "tags": [
        "cat.semantics",
        "best-practice"
      ],
      "description": "Ensure landmarks are unique",
      "help": "Landmarks should have a unique role or role/label/title (i.e. accessible name) combination",
      "helpUrl": "https://dequeuniversity.com/rules/axe/4.11/landmark-unique?application=axeAPI",
      "nodes": [
        {
          "any": [
            {
              "id": "landmark-is-unique",
              "data": {
                "role": "complementary",
                "accessibleText": null
              },
              "relatedNodes": [
                {
                  "html": "<aside class=\"w-64 bg-white border-r h-screen flex flex-col\">",
                  "target": [
                    "main > .bg-gray-50.h-screen.flex > aside"
                  ]
                }
              ],
              "impact": "moderate",
              "message": "The landmark must have a unique aria-label, aria-labelledby, or title to make landmarks distinguishable"
            }
          ],
          "all": [],
          "none": [],
          "impact": "moderate",
          "html": "<aside class=\"w-64 bg-white border-r h-screen flex flex-col\">",
          "target": [
            "body > .bg-gray-50.h-screen.flex > aside"
          ],
          "failureSummary": "Fix any of the following:\n  The landmark must have a unique aria-label, aria-labelledby, or title to make landmarks distinguishable"
        },
        {
          "any": [
            {
              "id": "landmark-is-unique",
              "data": {
                "role": "navigation",
                "accessibleText": null
              },
              "relatedNodes": [
                {
                  "html": "<nav class=\"flex-1 overflow-y-auto px-3 py-4 space-y-2\">",
                  "target": [
                    "main > .bg-gray-50.h-screen.flex > aside > nav"
                  ]
                }
              ],
              "impact": "moderate",
              "message": "The landmark must have a unique aria-label, aria-labelledby, or title to make landmarks distinguishable"
            }
          ],
          "all": [],
          "none": [],
          "impact": "moderate",
          "html": "<nav class=\"flex-1 overflow-y-auto px-3 py-4 space-y-2\">",
          "target": [
            "body > .bg-gray-50.h-screen.flex > aside > nav"
          ],
          "failureSummary": "Fix any of the following:\n  The landmark must have a unique aria-label, aria-labelledby, or title to make landmarks distinguishable"
        },
        {
          "any": [
            {
              "id": "landmark-is-unique",
              "data": {
                "role": "main",
                "accessibleText": null
              },
              "relatedNodes": [
                {
                  "html": "<main class=\"flex-1 overflow-y-auto p-6\">",
                  "target": [
                    "main > .bg-gray-50.h-screen.flex > main"
                  ]
                }
              ],
              "impact": "moderate",
              "message": "The landmark must have a unique aria-label, aria-labelledby, or title to make landmarks distinguishable"
            }
          ],
          "all": [],
          "none": [],
          "impact": "moderate",
          "html": "<main class=\"flex-1 overflow-y-auto p-6\">",
          "target": [
            "body > .bg-gray-50.h-screen.flex > main"
          ],
          "failureSummary": "Fix any of the following:\n  The landmark must have a unique aria-label, aria-labelledby, or title to make landmarks distinguishable"
        }
      ]
    }
  ]
}